{
    "title": "Alien Workshop KOTR",
    "description": "Alien Workshop team in Thrasher's 2012 King of the Road\n\nMusic:\n\"Wreck Everything\"\nPerformed by Get Killed\nwww.corleonerecords.com\n\n\"Draculala\"\nPerformed by Shiny Darkly\nFrom the album \"Shiny Darkly\"\nPublished by Crunchy Tunes\n(p) 2012 Crunchy Frog\n\n\"Depakote Composition\"\nPerformed by Nicholas Andrew Sadler\n\n\n\u00a9 2013 Alien Workshop",
    "referenceId": null,
    "date_created": "1401234434",
    "date_modified": "1443475096",
    "tags": "",
    "sourceId": "4",
    "VIDEO_LENGTH": "LONG",
    "status": "approved",
    "visibility": "1",
    "video_brand": null,
    "video_celeb": null,
    "video_activity": null,
    "VV_VI": null,
    "CVV_VI": null,
    "engagement_score": null,
    "conversion_score": null,
    "id": "169269",
    "loginId": "753",
    "entityType": "1",
    "sortOrder": "9",
    "entityIdParent": "168555",
    "titleTextEncoded": "Alien-Workshop-KOTR",
    "category": null,
    "duration": "607",
    "settings": [],
    "asset": {
        "author": "Alien Workshop",
        "videoId": "ROIHtmbVh9M",
        "hookText": "Alien Workshop team in Thrasher's 2012 King of the Road Music: \"Wreck Everything\" Performed by Get Killed www.corleonerecords.com \"Draculala\" Performed by Sh...",
        "thumbnailUrl": "https:\/\/i.ytimg.com\/vi\/ROIHtmbVh9M\/maxresdefault.jpg",
        "mediaDuration": "607",
        "hdvFlag": 1,
        "uploadDate": 1365724007,
        "prettyDuration": "00:10:07"
    },
    "transcripts": null,
    "metrics_statistics": null,
    "tvp_profiles": null,
    "tvp_profiles_manual": null,
    "tvp_profiles_maxscore": null
}