{
    "title": "BEHIND THE SCENES: CHAPTER ONE",
    "description": "JP interviews 20-year-old boardshort designer, Carson Wach. Video: Mark Choiniere.",
    "referenceId": null,
    "date_created": "1440440863",
    "date_modified": "1440440863",
    "tags": "",
    "sourceId": "4",
    "VIDEO_LENGTH": "SHORT",
    "status": "approved",
    "visibility": "1",
    "video_brand": null,
    "video_celeb": null,
    "video_activity": null,
    "VV_VI": null,
    "CVV_VI": null,
    "engagement_score": null,
    "conversion_score": null,
    "id": "6378705",
    "loginId": "753",
    "entityType": "1",
    "titleTextEncoded": "BEHIND-THE-SCENES-CHAPTER-ONE",
    "category": null,
    "duration": "110",
    "settings": {},
    "asset": {
        "type": "youtube",
        "thumbnailUrl": "https:\/\/i.ytimg.com\/vi\/wX3WwD8NZSM\/hqdefault.jpg",
        "uploadDate": 1296019656,
        "videoId": "wX3WwD8NZSM",
        "title": "BEHIND THE SCENES: CHAPTER ONE",
        "description": "JP interviews 20-year-old boardshort designer, Carson Wach. Video: Mark Choiniere.",
        "author": "hurley",
        "mediaDuration": "110",
        "prettyDuration": "00:01:50",
        "views": "389",
        "hookText": "JP interviews 20-year-old boardshort designer, Carson Wach. Video: Mark Choiniere."
    },
    "transcripts": null,
    "metrics_statistics": null,
    "tvp_profiles": null,
    "tvp_profiles_manual": null,
    "tvp_profiles_maxscore": null
}