{
    "title": "SPY + TSL + EVO",
    "description": "SPY teamed up with Push from The Seventh Letter to provide a facelift on the wall of Pacific Northwest retailer EVO to spice up the neighborhood. The piece currently graces the west side wall at the corner of 2nd and 36th Streets in Seattle, home of EVO's retail showroom. Check out the continuing collaboration between SPY and The Seventh Letter over at www.spyoptic.com\/collection\/artist-colla\u00adbs.",
    "referenceId": null,
    "date_created": "1440443927",
    "date_modified": "1444781734",
    "tags": "",
    "sourceId": "4",
    "VIDEO_LENGTH": "SHORT",
    "status": "approved",
    "visibility": "1",
    "video_brand": null,
    "video_celeb": null,
    "video_activity": null,
    "VV_VI": null,
    "CVV_VI": null,
    "engagement_score": null,
    "conversion_score": null,
    "id": "6379616",
    "loginId": "753",
    "entityType": "1",
    "titleTextEncoded": "SPY-TSL-EVO",
    "category": null,
    "duration": "73",
    "settings": {},
    "asset": {
        "type": "youtube",
        "thumbnailUrl": "https:\/\/i.ytimg.com\/vi\/4cbq-GCTvjo\/hqdefault.jpg",
        "uploadDate": 1346352430,
        "videoId": "4cbq-GCTvjo",
        "title": "SPY + TSL + EVO",
        "description": "SPY teamed up with Push from The Seventh Letter to provide a facelift on the wall of Pacific Northwest retailer EVO to spice up the neighborhood. The piece ...",
        "author": "spyoptic",
        "mediaDuration": "73",
        "prettyDuration": "00:01:13",
        "views": "2643",
        "hookText": "SPY teamed up with Push from The Seventh Letter to provide a facelift on the wall of Pacific Northwest retailer EVO to spice up the neighborhood. The piece ..."
    },
    "transcripts": null,
    "metrics_statistics": null,
    "tvp_profiles": null,
    "tvp_profiles_manual": null,
    "tvp_profiles_maxscore": null
}