{
    "title": "Maloof Money Clip: Day 1",
    "description": "Tyler Bledsoe, Sean Malto, Davis Torgerson at the Maloof Money Cup 09: day one.",
    "referenceId": null,
    "date_created": "1440443600",
    "date_modified": "1444409825",
    "tags": "etnies Skate,Tyler Bledsoe,Sean Malto,Davis Torgerson,Maloof Money Cup 09",
    "sourceId": "3",
    "VIDEO_LENGTH": "SHORT",
    "status": "approved",
    "visibility": "1",
    "video_brand": null,
    "video_celeb": null,
    "video_activity": null,
    "VV_VI": null,
    "CVV_VI": null,
    "engagement_score": null,
    "conversion_score": null,
    "id": "6379532",
    "loginId": "753",
    "entityType": "1",
    "titleTextEncoded": "Maloof-Money-Clip-Day-1",
    "category": null,
    "duration": 62,
    "settings": {},
    "asset": {
        "type": "mp4",
        "hdvFlag": 0,
        "thumbnailUrl": "https:\/\/i.vimeocdn.com\/video\/23136207_295x166.jpg",
        "mediaDuration": 62,
        "prettyDuration": "01:02",
        "uploadDate": 1251234187,
        "tags": "etnies Skate,Tyler Bledsoe,Sean Malto,Davis Torgerson,Maloof Money Cup 09",
        "hookText": "Tyler Bledsoe, Sean Malto, Davis Torgerson at the Maloof Money Cup 09: day one.",
        "sources": []
    },
    "transcripts": null,
    "metrics_statistics": null,
    "tvp_profiles": null,
    "tvp_profiles_manual": null,
    "tvp_profiles_maxscore": null
}