{
    "title": "Theotis Beasley Sponsor Me Review #35 El Mehdi Anys",
    "description": "http:\/\/facebook.com & http:\/\/twitter.com\/Altamont http:\/\/altamontapparel.com.",
    "referenceId": null,
    "date_created": "1440442686",
    "date_modified": "1440442686",
    "tags": "",
    "sourceId": "4",
    "VIDEO_LENGTH": "LONG",
    "status": "approved",
    "visibility": "1",
    "video_brand": null,
    "video_celeb": null,
    "video_activity": null,
    "VV_VI": null,
    "CVV_VI": null,
    "engagement_score": null,
    "conversion_score": null,
    "id": "6379084",
    "loginId": "753",
    "entityType": "1",
    "titleTextEncoded": "Theotis-Beasley-Sponsor-Me-Review-35-El-Mehdi-Anys",
    "category": null,
    "duration": "293",
    "settings": {},
    "asset": {
        "type": "youtube",
        "thumbnailUrl": "https:\/\/i.ytimg.com\/vi\/Cn2PVujK8F8\/hqdefault.jpg",
        "uploadDate": 1319672150,
        "videoId": "Cn2PVujK8F8",
        "title": "Theotis Beasley Sponsor Me Review #35 El Mehdi Anys",
        "description": "http:\/\/facebook.com & http:\/\/twitter.com\/Altamont http:\/\/altamontapparel.com.",
        "author": "Altamont",
        "mediaDuration": "293",
        "prettyDuration": "00:04:53",
        "views": "68037",
        "hookText": "http:\/\/facebook.com & http:\/\/twitter.com\/Altamont http:\/\/altamontapparel.com."
    },
    "transcripts": null,
    "metrics_statistics": null,
    "tvp_profiles": null,
    "tvp_profiles_manual": null,
    "tvp_profiles_maxscore": null
}