{
    "title": "Dakine Women's Mission Pack",
    "description": "Check out 360\u00b0 views of the 2013 Womens Mission pack in our Highland print.\nMission Features:\n- Vertical board carry straps\n- Fleece lined goggle pocket\n- Organizer pocket\n- Fleece lined sunglass pocket\n- Padded laptop sleeve\n- Fits most 15\" laptops\n- Padded waist belt",
    "referenceId": null,
    "date_created": "1440449966",
    "date_modified": "1444083946",
    "tags": "",
    "sourceId": "3",
    "VIDEO_LENGTH": "SHORT",
    "status": "approved",
    "visibility": "1",
    "video_brand": null,
    "video_celeb": null,
    "video_activity": null,
    "VV_VI": null,
    "CVV_VI": null,
    "engagement_score": null,
    "conversion_score": null,
    "id": "6380606",
    "loginId": "753",
    "entityType": "1",
    "titleTextEncoded": "Dakine-Women-s-Mission-Pack",
    "category": null,
    "duration": 67,
    "settings": {},
    "asset": {
        "type": "mp4",
        "hdvFlag": 1,
        "thumbnailUrl": "https:\/\/i.vimeocdn.com\/video\/333409469_1280x720.jpg",
        "mediaDuration": 67,
        "prettyDuration": "01:07",
        "uploadDate": 1345144095,
        "tags": "",
        "hookText": "Check out 360\u00b0 views of the 2013 Womens Mission pack in our Highland print.\nMission Features:\n- Vertical board carry straps\n- Fleece lined goggle pocket\n- Organizer pocket\n- Fleece lined sunglass pocket\n- Padded laptop sleeve\n- Fits most 15\" laptops\n- Pad",
        "sources": [
            {
                "file": "https:\/\/player.vimeo.com\/external\/47677516.hd.mp4?s=5f3b3add8a7e34d70de242ad906e4e2a&profile_id=113&oauth2_token_id=56801069"
            }
        ]
    },
    "transcripts": null,
    "metrics_statistics": null,
    "tvp_profiles": null,
    "tvp_profiles_manual": null,
    "tvp_profiles_maxscore": null
}