{
    "title": "Snowboarding Santa! | Presented by Neff",
    "description": "Our annual Snowboarding Santa edit! Check out Brandon Davis as he rips the mountain and passes out Neff Headwear beanies along the way.",
    "referenceId": null,
    "date_created": "1440628699",
    "date_modified": "1440628699",
    "tags": "",
    "sourceId": "4",
    "VIDEO_LENGTH": "SHORT",
    "status": "approved",
    "visibility": "1",
    "video_brand": null,
    "video_celeb": null,
    "video_activity": null,
    "VV_VI": "3",
    "CVV_VI": null,
    "engagement_score": null,
    "conversion_score": null,
    "id": "6383202",
    "loginId": "753",
    "entityType": "1",
    "titleTextEncoded": "Snowboarding-Santa-Presented-by-Neff",
    "category": null,
    "duration": "189",
    "settings": {},
    "asset": {
        "type": "youtube",
        "thumbnailUrl": "https:\/\/i.ytimg.com\/vi\/Rfm_O2sXjE0\/hqdefault.jpg",
        "uploadDate": 1419287805,
        "videoId": "Rfm_O2sXjE0",
        "title": "Snowboarding Santa! | Presented by Neff",
        "description": "Our annual Snowboarding Santa edit! Check out Brandon Davis as he rips the mountain and passes out Neff Headwear beanies along the way.",
        "author": "theneffheadwear",
        "mediaDuration": "189",
        "prettyDuration": "00:03:09",
        "views": "1103",
        "hookText": "Our annual Snowboarding Santa edit! Check out Brandon Davis as he rips the mountain and passes out Neff Headwear beanies along the way."
    },
    "transcripts": null,
    "metrics_statistics": "{\"VV_VI\":{\"lastUpdatedDate\":\"2017-05-24\",\"engagement_score\":{\"lastUpdatedDate\":\"2017-05-25\"}}}",
    "tvp_profiles": null,
    "tvp_profiles_manual": null,
    "tvp_profiles_maxscore": null
}