{
    "title": "Welcome to the Team - Chris Joslin",
    "description": "Arnette welcomes Chris Joslin to the team with a tour around San Diego's local skateparks, where we ran into Pat Duffy and Willy Santos.\nOn location at Arnette HQ, Rancho Penasquitos, Prince Park and Alga Norte.",
    "referenceId": null,
    "date_created": "1440637614",
    "date_modified": "1445964410",
    "tags": "",
    "sourceId": "4",
    "VIDEO_LENGTH": "SHORT",
    "status": "approved",
    "visibility": "1",
    "video_brand": null,
    "video_celeb": null,
    "video_activity": null,
    "VV_VI": "1",
    "CVV_VI": null,
    "engagement_score": null,
    "conversion_score": null,
    "id": "6383263",
    "loginId": "753",
    "entityType": "1",
    "sortOrder": "21",
    "entityIdParent": "168553",
    "titleTextEncoded": "Welcome-to-the-Team-Chris-Joslin",
    "category": null,
    "duration": "150",
    "settings": {},
    "asset": {
        "type": "youtube",
        "thumbnailUrl": "https:\/\/i.ytimg.com\/vi\/XRLmDgD6LmM\/hqdefault.jpg",
        "uploadDate": 1421773535,
        "videoId": "XRLmDgD6LmM",
        "title": "Welcome to the Team - Chris Joslin",
        "description": "Arnette welcomes Chris Joslin to the team with a tour around San Diego's local skateparks, where we ran into Pat Duffy and Willy Santos. On location at Arnette ...",
        "author": "Arnette",
        "mediaDuration": "150",
        "prettyDuration": "00:02:30",
        "views": "37245",
        "hookText": "Arnette welcomes Chris Joslin to the team with a tour around San Diego's local skateparks, where we ran into Pat Duffy and Willy Santos. On location at Arnette ..."
    },
    "transcripts": null,
    "metrics_statistics": {
        "VV_VI": {
            "lastUpdatedDate": "2017-05-24",
            "engagement_score": {
                "lastUpdatedDate": "2017-05-25"
            }
        }
    },
    "tvp_profiles": null,
    "tvp_profiles_manual": null,
    "tvp_profiles_maxscore": null
}