{
    "title": "Danilo Couto XXL Interview",
    "description": "O'Neill Rider Danilo Couto tells us about his $50000 dollar ride.",
    "referenceId": "VpCmII5NjBU",
    "date_created": "1444247094",
    "date_modified": "1444247094",
    "tags": "",
    "sourceId": "4",
    "VIDEO_LENGTH": "LONG",
    "status": "approved",
    "visibility": "1",
    "video_brand": null,
    "video_celeb": null,
    "video_activity": null,
    "VV_VI": "1",
    "CVV_VI": null,
    "engagement_score": null,
    "conversion_score": null,
    "id": "6419984",
    "loginId": "753",
    "entityType": "1",
    "titleTextEncoded": "Danilo-Couto-XXL-Interview",
    "category": null,
    "duration": "305",
    "settings": {},
    "asset": {
        "type": "youtube",
        "thumbnailUrl": "https:\/\/i.ytimg.com\/vi\/VpCmII5NjBU\/hqdefault.jpg",
        "uploadDate": 1304469005,
        "videoId": "VpCmII5NjBU",
        "title": "Danilo Couto XXL Interview",
        "description": "O'Neill Rider Danilo Couto tells us about his $50000 dollar ride.",
        "author": "TeamONeill",
        "mediaDuration": "305",
        "prettyDuration": "00:05:05",
        "views": "653",
        "hookText": "O'Neill Rider Danilo Couto tells us about his $50000 dollar ride."
    },
    "transcripts": null,
    "metrics_statistics": "{\"VV_VI\":{\"lastUpdatedDate\":\"2017-05-24\",\"engagement_score\":{\"lastUpdatedDate\":\"2017-05-25\"}}}",
    "tvp_profiles": null,
    "tvp_profiles_manual": null,
    "tvp_profiles_maxscore": null
}