{
    "title": "Sanuk Tutorial: How to Tie Women's Yoga Slinged Up",
    "description": "A quick visual tutorial on how to tie the Women's Yoga Slinged Up sandal.",
    "referenceId": "z4vrIqQ3et0",
    "date_created": "1418077333",
    "date_modified": "1468953770",
    "tags": "",
    "sourceId": "4",
    "VIDEO_LENGTH": "SHORT",
    "status": "approved",
    "visibility": "1",
    "video_brand": null,
    "video_celeb": null,
    "video_activity": null,
    "VV_VI": "9",
    "CVV_VI": null,
    "engagement_score": null,
    "conversion_score": null,
    "id": "66177833",
    "loginId": "753",
    "entityType": "1",
    "sortOrder": "8",
    "entityIdParent": "3764432",
    "titleTextEncoded": "Sanuk-Tutorial-How-to-Tie-Women-s-Yoga-Slinged-Up",
    "category": "",
    "duration": 40,
    "settings": "",
    "asset": {
        "type": "youtube",
        "thumbnailUrl": "https:\/\/i.ytimg.com\/vi\/z4vrIqQ3et0\/hqdefault.jpg",
        "uploadDate": 1418077333,
        "videoId": "z4vrIqQ3et0",
        "title": "Sanuk Tutorial: How to Tie Women's Yoga Slinged Up",
        "description": "A quick visual tutorial on how to tie the Women's Yoga Slinged Up sandal.\n\nwww.sanuk.com",
        "author": "Sanuk Footwear",
        "mediaDuration": 40,
        "prettyDuration": "00:00:40",
        "views": "5652",
        "uploadAsset": false,
        "quality": ""
    },
    "transcripts": "The Yoga Slinged Up how to tutorial. Step 1: grab both straps. Step 2: Cross behind ankles. Step 3: Wrap longer strap around ankle again. Step 4: Tie straps and style. Step 5: enjoy your new Yoga Slinged Up.",
    "metrics_statistics": {
        "VV_VI": {
            "lastUpdatedDate": "2017-05-24",
            "engagement_score": {
                "lastUpdatedDate": "2017-05-25"
            }
        }
    },
    "tvp_profiles": null,
    "tvp_profiles_manual": null,
    "tvp_profiles_maxscore": null
}